[
  {
    "id": "book_0001",
    "title": "How to Code - Intro for firsttimers",
    "author": "Joshua Mulongo",
    "pages": 23,
    "tag": "firsttimercoder,newbieDev",
    "dateAdded": "2026-06-17",
    "updatedAt": "2026-06-18T15:18:23.887Z"
  },
  {
    "id": "book_0002",
    "title": "How to Understand Women",
    "author": "Broke Guy",
    "pages": 1,
    "tag": "Humor,Relationships",
    "dateAdded": "2026-06-17",
    "updatedAt": "2026-06-18T15:18:23.887Z"
  },
  {
    "id": "book_0003",
    "title": "How to cook Matooke",
    "author": "Joshua Mulongo",
    "pages": 10,
    "tag": "Cooking,African-Dishes",
    "dateAdded": "2026-06-03",
    "updatedAt": "2026-06-18T15:18:23.888Z"
  },
  {
    "id": "book_0004",
    "title": "JavaScript Basics for Beginners",
    "author": "Sarah Nankunda",
    "pages": 45,
    "tag": "JavaScript,Programming",
    "dateAdded": "2026-06-05",
    "updatedAt": "2026-06-18T15:18:23.889Z"
  },
  {
    "id": "book_0005",
    "title": "Mastering React in 30 Days",
    "author": "Kevin Mwangi",
    "pages": 120,
    "tag": "React,Frontend",
    "dateAdded": "2026-06-07",
    "updatedAt": "2026-06-18T15:18:23.889Z"
  },
  {
    "id": "book_0006",
    "title": "The Art of Public Speaking",
    "author": "Grace Mukasa",
    "pages": 78,
    "tag": "Communication,Self-Improvement",
    "dateAdded": "2026-06-08",
    "updatedAt": "2026-06-18T15:18:23.890Z"
  },
  {
    "id": "book_0007",
    "title": "Healthy Living on a Budget",
    "author": "Daniel Kato",
    "pages": 56,
    "tag": "Health,Lifestyle",
    "dateAdded": "2026-06-09",
    "updatedAt": "2026-06-18T15:18:23.890Z"
  },
  {
    "id": "book_0008",
    "title": "Git and GitHub Essentials",
    "author": "Joshua Mulongo",
    "pages": 38,
    "tag": "Git,Version-Control",
    "dateAdded": "2026-06-10",
    "updatedAt": "2026-06-18T15:18:23.891Z"
  },
  {
    "id": "book_0009",
    "title": "Starting a Small Business",
    "author": "Amina Hassan",
    "pages": 95,
    "tag": "Business,Entrepreneurship",
    "dateAdded": "2026-06-11",
    "updatedAt": "2026-06-18T15:18:23.891Z"
  },
  {
    "id": "book_0010",
    "title": "Python for Data Analysis",
    "author": "Michael Otieno",
    "pages": 150,
    "tag": "Python,DataScience",
    "dateAdded": "2026-06-12",
    "updatedAt": "2026-06-18T15:18:23.892Z"
  },
  {
    "id": "book_0011",
    "title": "Travel Guide to East Africa",
    "author": "Linda Namusoke",
    "pages": 82,
    "tag": "Travel,Africa",
    "dateAdded": "2026-06-14",
    "updatedAt": "2026-06-18T15:18:23.892Z"
  },
  {
    "id": "book_0012",
    "title": "Understanding Personal Finance",
    "author": "Peter Rukundo",
    "pages": 67,
    "tag": "Finance,Money-Management",
    "dateAdded": "2026-06-15",
    "updatedAt": "2026-06-18T15:18:23.893Z"
  },
  {
    "id": "book_0013",
    "title": "Introduction to Cybersecurity",
    "author": "Brian Tumusiime",
    "pages": 88,
    "tag": "Security,Technology",
    "dateAdded": "2026-06-16",
    "updatedAt": "2026-06-18T15:18:23.894Z"
  },
  {
    "id": "book_0014",
    "title": "Building Mobile Apps with Flutter",
    "author": "Esther Uwimana",
    "pages": 134,
    "tag": "Flutter,Mobile-Development",
    "dateAdded": "2026-06-17",
    "updatedAt": "2026-06-18T15:18:23.894Z"
  }
]